setup.py
debade_courier/__init__.py
debade_courier.egg-info/PKG-INFO
debade_courier.egg-info/SOURCES.txt
debade_courier.egg-info/dependency_links.txt
debade_courier.egg-info/entry_points.txt
debade_courier.egg-info/requires.txt
debade_courier.egg-info/top_level.txt