Metadata-Version: 1.1
Name: debade-courier
Version: 0.3.0
Summary: DeBaDe Courier
Home-page: https://github.com/iamfat/debade-courier
Author: Jia Huang
Author-email: iamfat@gmail.com
License: MIT
Keywords: debade courier
Platform: UNKNOWN
Classifier: Development Status :: 3 - Alpha
Classifier: Intended Audience :: Developers
Classifier: Topic :: Utilities
Classifier: License :: OSI Approved :: MIT License
